losant_rest/__init__.py
losant_rest/application.py
losant_rest/application_api_token.py
losant_rest/application_api_tokens.py
losant_rest/application_certificate.py
losant_rest/application_certificate_authorities.py
losant_rest/application_certificate_authority.py
losant_rest/application_certificates.py
losant_rest/application_dashboard.py
losant_rest/application_dashboards.py
losant_rest/application_job_log.py
losant_rest/application_job_logs.py
losant_rest/application_key.py
losant_rest/application_keys.py
losant_rest/application_template.py
losant_rest/application_templates.py
losant_rest/applications.py
losant_rest/audit_log.py
losant_rest/audit_logs.py
losant_rest/auth.py
losant_rest/client.py
losant_rest/credential.py
losant_rest/credentials.py
losant_rest/dashboard.py
losant_rest/dashboards.py
losant_rest/data.py
losant_rest/data_table.py
losant_rest/data_table_row.py
losant_rest/data_table_rows.py
losant_rest/data_tables.py
losant_rest/device.py
losant_rest/device_attribute.py
losant_rest/device_attributes.py
losant_rest/device_recipe.py
losant_rest/device_recipes.py
losant_rest/devices.py
losant_rest/edge_deployment.py
losant_rest/edge_deployments.py
losant_rest/embedded_deployment.py
losant_rest/embedded_deployments.py
losant_rest/event.py
losant_rest/events.py
losant_rest/experience.py
losant_rest/experience_domain.py
losant_rest/experience_domains.py
losant_rest/experience_endpoint.py
losant_rest/experience_endpoints.py
losant_rest/experience_group.py
losant_rest/experience_groups.py
losant_rest/experience_slug.py
losant_rest/experience_slugs.py
losant_rest/experience_user.py
losant_rest/experience_users.py
losant_rest/experience_version.py
losant_rest/experience_versions.py
losant_rest/experience_view.py
losant_rest/experience_views.py
losant_rest/file.py
losant_rest/files.py
losant_rest/flow.py
losant_rest/flow_version.py
losant_rest/flow_versions.py
losant_rest/flows.py
losant_rest/instance.py
losant_rest/instance_api_token.py
losant_rest-2.0.3.dist-info/LICENSE
losant_rest-2.0.3.dist-info/METADATA
losant_rest-2.0.3.dist-info/WHEEL
losant_rest-2.0.3.dist-info/top_level.txt
losant_rest-2.0.3.dist-info/RECORD
