Metadata-Version: 2.1
Name: losant-rest
Version: 2.0.3
Summary: A REST client for the Losant API
Home-page: https://github.com/Losant/losant-rest-python
Author: Losant
Author-email: hello@losant.com
License: MIT
Keywords: REST,Losant,IoT
Classifier: Development Status :: 4 - Beta
Classifier: Intended Audience :: Developers
Classifier: Operating System :: MacOS :: MacOS X
Classifier: Operating System :: Microsoft :: Windows
Classifier: Operating System :: POSIX
Classifier: Topic :: Communications
Classifier: Topic :: Internet
Classifier: Topic :: Software Development :: Libraries
Classifier: License :: OSI Approved :: MIT License
Classifier: Programming Language :: Python
Classifier: Programming Language :: Python :: 2.7
Classifier: Programming Language :: Python :: 3
License-File: LICENSE
Requires-Dist: requests >=2.13
Provides-Extra: test
Requires-Dist: tox ; extra == 'test'
